[
  {
    "name": "基础组件",
    "groups": [
      {
        "groupName": "Basic 基础",
        "list": [
          {
            "path": "/button",
            "title": "Button 按钮"
          },
          {
            "path": "/icon",
            "title": "Icon 图标"
          },
          {
            "path": "/grid",
            "title": "Grid 栅格系统"
          },
          {
            "path": "/switch",
            "title": "Switch 开关"
          },
          {
            "path": "/breadcrumb",
            "title": "Breadcrumb 面包屑"
          },
          {
            "path": "/input",
            "title": "Input 输入框"
          },
          {
            "path": "/chip",
            "title": "Chip 信息块"
          },
          {
            "path": "/radio",
            "title": "Radio 单选框"
          }
        ]
      }
    ]
  }
]
